{
  "consumes": [
    "application/json"
  ],
  "produces": [
    "application/json"
  ],
  "schemes": [
    "http"
  ],
  "swagger": "2.0",
  "info": {
    "description": "This is a simple kipchoge keino jokes API for learning purpose",
    "title": "Kipchoge API",
    "contact": {
      "name": "Marvin Collins",
      "url": "https://appslab.co.ke",
      "email": "marvin@appslab.co.ke"
    },
    "license": {
      "name": "MIT"
    },
    "version": "1.0.0"
  },
  "host": "localhost:9001",
  "basePath": "/",
  "paths": {}
}